nanogcg/__init__.py
nanogcg/gcg.py
nanogcg/utils.py
nanogcg-0.2.3.dist-info/LICENSE
nanogcg-0.2.3.dist-info/METADATA
nanogcg-0.2.3.dist-info/WHEEL
nanogcg-0.2.3.dist-info/top_level.txt
nanogcg-0.2.3.dist-info/RECORD
