Metadata-Version: 2.1
Name: nanogcg
Version: 0.2.3
Summary: A lightweight implementation of the GCG algorithm
Author-email: Justin Wang <justin@grayswan.ai>
Project-URL: Homepage, https://github.com/GraySwanAI/nanoGCG
Project-URL: Issues, https://github.com/GraySwanAI/nanoGCG/issues
Classifier: Programming Language :: Python :: 3
Classifier: License :: OSI Approved :: MIT License
Classifier: Operating System :: OS Independent
Requires-Python: >=3.9
License-File: LICENSE
Requires-Dist: torch>=2.0
Requires-Dist: transformers>=4.4
